crkpk/__init__.py
crkpk-1.dist-info/METADATA
crkpk-1.dist-info/WHEEL
crkpk-1.dist-info/entry_points.txt
crkpk-1.dist-info/top_level.txt
crkpk-1.dist-info/RECORD
