Metadata-Version: 2.1
Name: crkpk
Version: 1
Summary: Pakistani Facebook Account Cloner
Home-page: https://github.com/htr-tech
Author: HTR-TECH
Author-email: unknown@email.com
License: MIT
Platform: UNKNOWN
Classifier: Programming Language :: Python :: 2
Classifier: License :: OSI Approved :: MIT License
Classifier: Operating System :: OS Independent
Requires-Python: >=2.7
